abbr/views.py
abbr/app.py
abbr/validation.py
abbr/config.py
abbr/utils.py
abbr/db.py
abbr-0.0.0.dist-info/top_level.txt
abbr-0.0.0.dist-info/DESCRIPTION.rst
abbr-0.0.0.dist-info/WHEEL
abbr-0.0.0.dist-info/metadata.json
abbr-0.0.0.dist-info/RECORD
abbr-0.0.0.dist-info/METADATA
