Metadata-Version: 2.0
Name: abbr
Version: 0.0.0
Summary: Self-hosted URL shortener
Home-page: https://github.com/rixx/abbr
Author: Tobias Kunze
Author-email: rixx@cutebit.de
License: Apache Software License
Platform: UNKNOWN
Classifier: License :: OSI Approved :: Apache Software License
Classifier: Programming Language :: Python :: 3
Classifier: Programming Language :: Python :: 3.5
Classifier: Programming Language :: Python :: 3.6
Requires-Dist: Flask (==0.11.1)
